examples/basic/composition.nix
examples/basic/flake.nix
examples/basic/nxc.json
examples/basic-nur/composition.nix
examples/basic-nur/flake.nix
examples/basic-nur/nxc.json
examples/execo/composition.nix
examples/execo/execo_script.py
examples/execo/flake.nix
examples/execo/nxc.json
examples/flake.lock
examples/kernel/compositions.nix
examples/kernel/flake.nix
examples/kernel/linux_5_4.nix
examples/kernel/linux_ipanema_5_4.nix
examples/kernel/nxc.json
examples/multi-compositions/bar-composition.nix
examples/multi-compositions/compositions.nix
examples/multi-compositions/flake.nix
examples/multi-compositions/foo-composition.nix
examples/multi-compositions/nxc.json
examples/nbp-mpi/composition.nix
examples/nbp-mpi/flake.nix
examples/nbp-mpi/nxc.json
examples/nix_flake_templates.nix
examples/nixos-cluster/composition.nix
examples/nixos-cluster/flake.nix
examples/nixos-cluster/nodes.yaml
examples/nixos-cluster/nxc.json
examples/nixos-cluster/ssh-keys.nix
examples/scripts/composition.nix
examples/scripts/flake.nix
examples/scripts/nxc.json
examples/scripts/scripts/scripts.nix
examples/scripts/scripts/test_python.py
examples/setup/composition.nix
examples/setup/flake.nix
examples/setup/nxc.json
examples/setup/setup.toml
examples/shared-directories-users/composition.nix
examples/shared-directories-users/flake.nix
examples/shared-directories-users/nxc.json
examples/webserver/composition.nix
examples/webserver/flake.nix
examples/webserver/nxc.json
nix/all-in-one.nix
nix/compose.nix
nix/flavours/docker/base.nix
nix/flavours/docker/generate_docker_compose.nix
nix/flavours/docker/generate_image.nix
nix/flavours/docker/nxc-shared-dirs-docker.nix
nix/flavours/docker.nix
nix/flavours/g5k-image.nix
nix/flavours/g5k-nfs-store.nix
nix/flavours/g5k-ramdisk.nix
nix/flavours/nspawn/base.nix
nix/flavours/nspawn/generate_nspawn_compose.nix
nix/flavours/nspawn.nix
nix/flavours/shared/base-hardware.nix
nix/flavours/shared/base-vm.nix
nix/flavours/shared/base.nix
nixos_compose-0.7.8.dist-info/LICENSE
nixos_compose-0.7.8.dist-info/METADATA
nixos_compose-0.7.8.dist-info/WHEEL
nixos_compose-0.7.8.dist-info/entry_points.txt
nixos_compose-0.7.8.dist-info/RECORD
