Metadata-Version: 2.3
Name: nixos-compose
Version: 0.7.8
Summary: 
License: MIT
Author: Olivier Richard
Author-email: olivier.richard@imag.fr
Requires-Python: >=3.7,<4.0
Classifier: License :: OSI Approved :: MIT License
Classifier: Programming Language :: Python :: 3
Classifier: Programming Language :: Python :: 3.7
Classifier: Programming Language :: Python :: 3.8
Classifier: Programming Language :: Python :: 3.9
Classifier: Programming Language :: Python :: 3.10
Classifier: Programming Language :: Python :: 3.11
Classifier: Programming Language :: Python :: 3.12
Classifier: Programming Language :: Python :: 3.13
Requires-Dist: PyYAML (>=6.0,<7.0)
Requires-Dist: click (>=7.1.2)
Requires-Dist: execo (>=2.6.8)
Requires-Dist: halo (>=0.0.31,<0.0.32)
Requires-Dist: pexpect (>=4.8.0,<5.0.0)
Requires-Dist: psutil (>=5.9.0)
Requires-Dist: ptpython (>=3.0.7,<4.0.0)
Requires-Dist: requests (>=2.27.1,<3.0.0)
Requires-Dist: tomlkit (>=0.11)
